kogiri/__init__.py
kogiri/_utils.py
kogiri/arrow_output.py
kogiri/csv_output.py
kogiri/kogiri_git.py
kogiri/ndjson_output.py
kogiri/np.py
kogiri/pprint_output.py
kogiri/tb_output.py
kogiri/torch.py
kogiri/visdom.py
kogiri-0.2.0.dist-info/LICENSE
kogiri-0.2.0.dist-info/METADATA
kogiri-0.2.0.dist-info/WHEEL
kogiri-0.2.0.dist-info/top_level.txt
kogiri-0.2.0.dist-info/RECORD
