Metadata-Version: 2.1
Name: kogiri
Version: 0.2.0
Summary: Log first, ask questions later.
Author-email: "K.R. Zentner" <krzentner@gmail.com>
License: MIT License
Project-URL: Homepage, https://github.com/krzentner/kogiri
Project-URL: Bug Reports, https://github.com/krzentner/kogiri/issues
Project-URL: Source, https://github.com/krzentner/kogiri
Classifier: Development Status :: 3 - Alpha
Classifier: Intended Audience :: Science/Research
Classifier: Topic :: Software Development :: Build Tools
Classifier: Topic :: System :: Distributed Computing
Classifier: License :: OSI Approved :: MIT License
Classifier: Programming Language :: Python :: 3
Classifier: Programming Language :: Python :: 3.8
Classifier: Programming Language :: Python :: 3.9
Classifier: Programming Language :: Python :: 3.10
Classifier: Programming Language :: Python :: 3.11
Classifier: Programming Language :: Python :: 3 :: Only
Requires-Python: >=3.8
License-File: LICENSE
Provides-Extra: dev
Provides-Extra: git
Requires-Dist: GitPython ; extra == 'git'
Provides-Extra: pyarrow
Requires-Dist: pyarrow ; extra == 'pyarrow'
Provides-Extra: recommended
Requires-Dist: GitPython ; extra == 'recommended'
Requires-Dist: pyarrow ; extra == 'recommended'
Requires-Dist: tensorboardX ; extra == 'recommended'
Provides-Extra: tensorboardx
Requires-Dist: tensorboardX ; extra == 'tensorboardx'
Provides-Extra: test
Requires-Dist: pytest ; extra == 'test'
Provides-Extra: torch
Requires-Dist: torch ; extra == 'torch'
Provides-Extra: wandb
Requires-Dist: wandb ; extra == 'wandb'
